ament_cmake_cpplint/_dummy.cpython-312-x86_64-linux-gnu.so
ros_ament_cmake_cpplint-0.17.3.data/data/share/ament_cmake_cpplint/local_setup.bash
ros_ament_cmake_cpplint-0.17.3.data/data/share/ament_cmake_cpplint/local_setup.dsv
ros_ament_cmake_cpplint-0.17.3.data/data/share/ament_cmake_cpplint/local_setup.sh
ros_ament_cmake_cpplint-0.17.3.data/data/share/ament_cmake_cpplint/local_setup.zsh
ros_ament_cmake_cpplint-0.17.3.data/data/share/ament_cmake_cpplint/package.dsv
ros_ament_cmake_cpplint-0.17.3.data/data/share/ament_cmake_cpplint/package.xml
ros_ament_cmake_cpplint-0.17.3.data/data/share/ament_cmake_cpplint/cmake/ament_cmake_cpplint-extras.cmake
ros_ament_cmake_cpplint-0.17.3.data/data/share/ament_cmake_cpplint/cmake/ament_cmake_cpplintConfig-version.cmake
ros_ament_cmake_cpplint-0.17.3.data/data/share/ament_cmake_cpplint/cmake/ament_cmake_cpplintConfig.cmake
ros_ament_cmake_cpplint-0.17.3.data/data/share/ament_cmake_cpplint/cmake/ament_cmake_cpplint_lint_hook.cmake
ros_ament_cmake_cpplint-0.17.3.data/data/share/ament_cmake_cpplint/cmake/ament_cpplint.cmake
ros_ament_cmake_cpplint-0.17.3.data/data/share/ament_cmake_cpplint/environment/ament_prefix_path.dsv
ros_ament_cmake_cpplint-0.17.3.data/data/share/ament_cmake_cpplint/environment/ament_prefix_path.sh
ros_ament_cmake_cpplint-0.17.3.data/data/share/ament_cmake_cpplint/environment/path.dsv
ros_ament_cmake_cpplint-0.17.3.data/data/share/ament_cmake_cpplint/environment/path.sh
ros_ament_cmake_cpplint-0.17.3.data/data/share/ament_index/resource_index/package_run_dependencies/ament_cmake_cpplint
ros_ament_cmake_cpplint-0.17.3.data/data/share/ament_index/resource_index/packages/ament_cmake_cpplint
ros_ament_cmake_cpplint-0.17.3.data/data/share/ament_index/resource_index/parent_prefix_path/ament_cmake_cpplint
ros_ament_cmake_cpplint-0.17.3.dist-info/METADATA
ros_ament_cmake_cpplint-0.17.3.dist-info/WHEEL
ros_ament_cmake_cpplint-0.17.3.dist-info/top_level.txt
ros_ament_cmake_cpplint-0.17.3.dist-info/RECORD
