Metadata-Version: 2.4
Name: ros-ament-cmake-cpplint
Version: 0.17.3
Summary: Wheel for the ament_cmake_cpplint (ros-ament-cmake-cpplint) ROS 2 package.
Dynamic: description
Dynamic: description-content-type
Dynamic: summary
